Metadata-Version: 1.1
Name: kaikobittrex
Version: 1.0.3
Summary: Python bindings for Kaiko Bittrex Historical trade data
Home-page: https://github.com/lookfwd/python-kaiko-bittrex
Author: Dimitrios Kouzis-Loukas
Author-email: lookfwd@gmail.com
License: UNKNOWN
Platform: UNKNOWN
Classifier: Programming Language :: Python
Classifier: Programming Language :: Python :: 2.7
Classifier: Operating System :: OS Independent
Classifier: License :: OSI Approved :: MIT License
Classifier: Development Status :: 5 - Production/Stable
Classifier: Topic :: Office/Business :: Financial
